thing3/__init__.py
thingthingthingx-0.69.dist-info/LICENSE
thingthingthingx-0.69.dist-info/METADATA
thingthingthingx-0.69.dist-info/WHEEL
thingthingthingx-0.69.dist-info/top_level.txt
thingthingthingx-0.69.dist-info/RECORD
