Metadata-Version: 2.2
Name: thingthingthingx
Version: 0.69
Summary: the
Author-email: unnamed7353 <unnamed7353@gmail.com>
Classifier: Programming Language :: Python :: 3
Classifier: License :: OSI Approved :: MIT License
Classifier: Operating System :: OS Independent
License-File: LICENSE
